Workbook
Name _ftnref1: Presentacion!$B$15
Name _Toc257447184: Presentacion!$B$17

Sheet Presentacion
B8: MUIT
B9: Análisis de Negocio TIC (NTIC)
B11: Caso 01 rev. 3.0, 2 de marzo de 2025
B13: Caso FiberCo de Telefónica: análisis de proyectos de inversión
B15: Autores : Profesores Luis Castejón Martín y Fernando Herrera González (ETSIT-UPM)
B17: Objetivo: practicar los conceptos de TVM, como el coste del capital WACC, la rentabilidad exigida por el accionista Ke, pagos de deuda, NPV, IRR, en diferentes proyectos de ahorro de costes y de inversión.
B18: Tipo de entrega: Individual.
B19: Formato de la entrega: se entregará la hoja de cálculo Excel proporcionada junto al caso, completada con los cálculos y la justificación argumental de las respuestas cuando proceda.
B20: Extensión de la entrega: no hay límites en el Excel.

Sheet Sit 01
B2: Telefónica, S.A.
C4: Value
B5: Selected Beta | C5: 1.81
B6: Market Risk Premium | C6: 0.058
B7: Risk-free Rate | C7: 0.024
B8: Additional Risk Adjustments | C8: 0.041
B9: Pre-tax Cost of Debt | C9: 0.058
B10: Tax Rate | C10: 0.26
B11: Debt % of Capital | C11: 0.675
B14: Ke | C14: =C7+C5*C6+C8 -> 0.16998
B15: Kd pretax | C15: =C9 -> 0.058
B16: Kd after tax | C16: =C15*(1-C10) -> 0.04292
C18: Value | D18: Weight | E18: Wighted value
B19: =B14 -> Ke | C19: =C14 -> 0.16998 | D19: =1-C11 -> 0.325 | E19: =C19*D19 -> 0.0552435
B20: =B16 -> Kd after tax | C20: =C16 -> 0.04292 | D20: =C11 -> 0.675 | E20: =C20*D20 -> 0.028971
D21: WACC | E21: =E19+E20 -> 0.0842145

Sheet Sit 02
B3: Caso a | C3: VCM | D3: GSF
C4: 0.162 | D4: 0.183
B7: Caso b | C7: https://www.cnmc.es/expedientes/waccdtsa00921
B8: valores de CNMC de WACC, Ke y Kd
B10: Kd | D10: 0.0216
B11: Ke | D11: =1.01%+0.71*5.5% -> 0.04915
B12: WACC después impuestos | D12: 0.0362
B13: WACC antes impuestos | D13: 0.0482
B17: 1. Como es 100% equity, el benchmark correcto es comparar con el Ke
B18: 2. Comparar IRR del fondo vs Ke corporativo
B19: Ke corp | C19: ='Sit 01'!C14 -> 0.16998
B20: =C3 -> VCM | C20: =C4 -> 0.162
B21: =D3 -> GSF | C21: =D4 -> 0.183
B22: 3. ¿Debería proponerse estos proyectos?
B23: VCM | C23: No debería promover este tipo de inversiones reguladas si su rentabilidad está limitada al WACC regulatorio, ya que no cubren el Ke corporativo.
B24: GSF | C24: Podría aceptarlas únicamente si generan crecimiento estratégico, permiten expansión futura o reducen riesgos
C25: Pero estrictamente en términos financieros no maximizan valor para el accionista.

Sheet Sit 03
B3: m€ | C3: 50
B4: IPC | C4: 0.025
B5: n | C5: 4
B6: Costes actuales anuales | C6: 50 | D6: =C6*(1+$C$4) -> 51.25 | E6: =D6*(1+$C$4) -> 52.53125 | F6: =E6*(1+$C$4) -> 53.844531
B7: WACC | C7: ='Sit 01'!E21 -> 0.0842145
B9: Costes actuales | C9: 0 | D9: 1 | E9: 2 | F9: 3 | G9: 4 | H9: 5
B10: Pago inicial | C10: 0
B11: Pagos recurrentes
B12: Flujo neto de caja ACTUAL | D12: =-C6 -> -50 | E12: =-D6 -> -51.25 | F12: =-E6 -> -52.53125 | G12: =-F6 -> -53.844531 | H12: =-G6 -> 0
B13: NPV costes actuales | D13: =NPV($C$7, D12:G12) -> -169.89616 | E13: =NPV($C$7, E12:H12) -> -134.20388 | F13: =NPV($C$7, F12:I12) -> -94.255795 | G13: =NPV($C$7, G12:J12) -> -49.66225 | H13: =NPV($C$7, H12:K12) -> 0
B15: Oferta proveedor 1 | C15: 0 | D15: 1 | E15: 2 | F15: 3 | G15: 4 | H15: 4
B16: Pago inicial | C16: 45
B17: Pagos recurrentes | D17: 35 | E17: 35 | F17: 35 | G17: 35 | H17: 35
B18: Flujo neto de caja P1 | C18: =-SUM(C16:C17) -> -45 | D18: =-SUM(D16:D17) -> -35 | E18: =-SUM(E16:E17) -> -35 | F18: =-SUM(F16:F17) -> -35 | G18: =-SUM(G16:G17) -> -35 | H18: =-SUM(H16:H17) -> -35
B19: NPV costes P1 | D19: =+C18+NPV($C$7, D18:G18) -> -159.84522 | E19: =+D18+NPV($C$7, E18:H18) -> -149.84522 | F19: =+E18+NPV($C$7, F18:I18) -> -124.51685 | G19: =+F18+NPV($C$7, G18:J18) -> -97.055465 | H19: =+G18+NPV($C$7, H18:K18) -> -67.281435
B20: NPV Ahorro P1 | D20: =D13-D19 -> -10.050946 | E20: =E13-E19 -> 15.641334 | F20: =F13-F19 -> 30.261053 | G20: =G13-G19 -> 47.393215 | H20: =H13-H19 -> 67.281435
B22: Oferta proveedor 2 | C22: 0 | D22: 1 | E22: 2 | F22: 3 | G22: 4 | H22: 4
B23: Pago inicial | C23: 150 | G23: 10 | H23: 10
B24: Pagos recurrentes
B25: Flujo neto de caja P2 | C25: =-SUM(C23:C24) -> -150 | D25: =-SUM(D23:D24) -> 0 | E25: =-SUM(E23:E24) -> 0 | F25: =-SUM(F23:F24) -> 0 | G25: =-SUM(G23:G24) -> -10 | H25: =-SUM(H23:H24) -> -10
B26: NPV costes P2 | D26: =C25+NPV($C$7,D25:G25) -> -157.23668 | E26: =D25+NPV($C$7,E25:H25) -> -15.082786 | F26: =E25+NPV($C$7,F25:I25) -> -16.352975 | G26: =F25+NPV($C$7,G25:J25) -> -17.730133 | H26: =G25+NPV($C$7,H25:K25) -> -19.223267
B27: NPV Ahorro P2 | D27: =D13-D26 -> -12.659485 | E27: =E13-E26 -> -119.1211 | F27: =F13-F26 -> -77.90282 | G27: =G13-G26 -> -31.932117 | H27: =H13-H26 -> 19.223267
B29: Oferta proveedor 3 | C29: 0 | D29: 1 | E29: 2 | F29: 3 | G29: 4 | H29: 4
B30: Pago inicial | G30: 210 | H30: 210
B31: Pagos recurrentes
B32: Flujo neto de caja P3 | C32: =-SUM(C30:C31) -> 0 | D32: =-SUM(D30:D31) -> 0 | E32: =-SUM(E30:E31) -> 0 | F32: =-SUM(F30:F31) -> 0 | G32: =-SUM(G30:G31) -> -210 | H32: =-SUM(H30:H31) -> -210
B33: NPV costes P3 | D33: =NPV($C$7,D32:G32) -> -151.97021 | E33: =NPV($C$7,E32:H32) -> -316.73851 | F33: =NPV($C$7,F32:I32) -> -343.41248 | G33: =NPV($C$7,G32:J32) -> -372.33279 | H33: =NPV($C$7,H32:K32) -> -193.68861
B34: NPV Ahorro P3 | D34: =D13-D33 -> -17.925957 | E34: =E13-E33 -> 182.53462 | F34: =F13-F33 -> 249.15669 | G34: =G13-G33 -> 322.67054 | H34: =H13-H33 -> 193.68861
B36: Oferta proveedor 4 | C36: 0 | D36: 1 | E36: 2 | F36: 3 | G36: 4 | H36: 4
B37: Pago inicial
B38: Pagos recurrentes | D38: 48 | E38: 48 | F38: 48 | G38: 48 | H38: 48
B39: Flujo neto de caja P4 | C39: =-SUM(C37:C38) -> 0 | D39: =-SUM(D37:D38) -> -48 | E39: =-SUM(E37:E38) -> -48 | F39: =-SUM(F37:F38) -> -48 | G39: =-SUM(G37:G38) -> -48 | H39: =-SUM(H37:H38) -> -48
B40: NPV costes P4 | D40: =NPV($C$7,D39:G39) -> -157.50201 | E40: =NPV($C$7,E39:H39) -> -157.50201 | F40: =NPV($C$7,F39:I39) -> -122.76596 | G40: =NPV($C$7,G39:J39) -> -85.104638 | H40: =NPV($C$7,H39:K39) -> -44.271682
B41: NPV Ahorro P4 | D41: =D13-D40 -> -12.394151 | E41: =E13-E40 -> 23.298128 | F41: =F13-F40 -> 28.510169 | G41: =G13-G40 -> 35.442388 | H41: =H13-H40 -> 44.271682
B43: Oferta | C43: PV | D43: PV Ahorro
B44: NPV costes actuales | C44: =D13 -> -169.89616
B45: NPV costes P1 | C45: =D19 -> -159.84522 | D45: =C45-$C$44 -> 10.050946
B46: NPV costes P2 | C46: =D26 -> -157.23668 | D46: =C46-$C$44 -> 12.659485
B47: NPV costes P3 | C47: =D33 -> -151.97021 | D47: =C47-$C$44 -> 17.925957
B48: NPV costes P4 | C48: =D40 -> -157.50201 | D48: =C48-$C$44 -> 12.394151

Sheet Sit 04
B2: EFECTO DE LA CAPITALIZACIÖN COMPUESTA
B4: Flujos netos de caja | C4: =-$C$10 -> -8.6115311 | D4: 2.6244331 | E4: 2.6244331 | F4: 2.6244331 | G4: 2.6244331
B5: Check fórmula PAGO | C5: =PMT($C$11,4,-$C$10) -> 2.6244331
B6: NPV deuda | C6: =NPV($C$11,D4:G4) -> 8.6115311
B7: IRR deuda | C7: =IRR(C4:G4) -> 0.0842145
B8: 0
B9: A. Invertir en otros proyectos con capital propio
B10: Capex | C10: =NPV($C$11,D4:G4) -> 8.6115311
B11: WACC | C11: ='Sit 01'!E21 -> 0.0842145
B14: VF @WACC Reinversión de las rentabilidades anuales | C14: =C4 -> -8.6115311 | D14: =D4 -> 2.6244331 | E14: =E4 -> 2.6244331 | F14: =F4 -> 2.6244331 | G14: =G4 -> 2.6244331
B15: VF(CF Año 1) | G15: =D4*(1+$C$11)^(4-1) -> 3.3448846
B16: VF(CF Año 2) | G16: =E4*(1+$C$11)^(4-2) -> 3.0850765
B17: VF(CF Año 3) | G17: =F4*(1+$C$11)^(4-3) -> 2.8454484
B18: VF(CF Año 4) | G18: =G4*(1+$C$11)^(4-4) -> 2.6244331
F19: Suma VF(Cfi) | G19: =SUM(G15:G18) -> 11.899843 | H19: +1,4 por la reinversion
B22: Interés simple sin reinversión | D22: =D6 -> 0 | E22: =E6 -> 0 | F22: =F6 -> 0 | G22: =G6 -> 0
F23: Suma interes simple | G23: =SUM(D4:G4) -> 10.497732
B26: ¿Qúe sucede si nos es posible reinvertir los retornos anuales si en el futuro bajan las tasas de reinversión?
B28: Si en el futuro bajan las tasas de reinversión, el valor futuro del proyecto disminuye y, en consecuencia, la rentabilidad efectiva del mismo se reduce. Esto ocurre porque la capitalización compuesta depende de la tasa a la que se reinvierten los flujos intermedios. Este fenómeno se conoce como riesgo de reinversión y explica por qué la IRR puede sobreestimar la rentabilidad real cuando no es posible reinvertir los flujos a la tasa inicialmente asumida.

Sheet Sit 05
E3: 0.08 | F3: 0.06 | G3: 0.05 | H3: 0.055 | I3: 0.06 | J3: 0.07
B4: CF Alemania (m€) | C4: 0 | D4: 1 | E4: 2 | F4: 3 | G4: 4 | H4: 5 | I4: 6 | J4: 7
B5: PV Capex anteriores 5 años | C5: -30000
B6: CF neto negocio | D6: 5201.7777 | E6: 5617.92 | F6: 5954.9951 | G6: 6252.7449 | H6: 6596.6459 | I6: 6992.4446 | J6: 7481.9158
B7: CF neto total | C7: =SUM(C5:C6) -> -30000 | D7: =SUM(D5:D6) -> 5201.7777 | E7: =SUM(E5:E6) -> 5617.92 | F7: =SUM(F5:F6) -> 5954.9951 | G7: =SUM(G5:G6) -> 6252.7449 | H7: =SUM(H5:H6) -> 6596.6459 | I7: =SUM(I5:I6) -> 6992.4446 | J7: =SUM(J5:J6) -> 7481.9158
B8: tir del proyecto | C8: =IRR(C7:J7) -> 0.099990856
B9: tir min exigida | C9: =C10*1.12 -> 0.09432024
B10: WACC (coste oportunidad) | C10: ='Sit 01'!E21 -> 0.0842145
B12: IRR minima exig/WACC | C12: =C9/C10 -> 1.12

Sheet Sit 06
B2: ALEMANIA INVIERTO 30000 | C2: 0 | D2: 1 | E2: 2 | F2: 3 | G2: 4 | H2: 5 | I2: 6 | J2: 7
B3: CF neto total | C3: ='Sit 05'!C7 -> -30000 | D3: ='Sit 05'!D7 -> 5201.7777 | E3: ='Sit 05'!E7 -> 5617.92 | F3: ='Sit 05'!F7 -> 5954.9951 | G3: ='Sit 05'!G7 -> 6252.7449 | H3: ='Sit 05'!H7 -> 6596.6459 | I3: ='Sit 05'!I7 -> 6992.4446 | J3: ='Sit 05'!J7 -> 7481.9158
B4: NPV @ WACC | D4: =C3+NPV('Sit 05'!$C$10,'Sit 06'!D3:J3) -> 1729.9381 | K4: (1) SUMA VF ALEMANIA
B5: VF(7) de los CF netos de cada año desde año 1 (no del 0) | E5: =E3*(1+$C$7)^(7-E2) -> 8416.889 | F5: =F3*(1+$C$7)^(7-F2) -> 8228.9089 | G5: =G3*(1+$C$7)^(7-G2) -> 7969.2297 | H5: =H3*(1+$C$7)^(7-H2) -> 7754.4963 | I5: =I3*(1+$C$7)^(7-I2) -> 7581.3099 | J5: =J3*(1+$C$7)^(7-J2) -> 7481.9158 | K5: =SUM(D5:J5) -> 47432.75
B7: WACC | C7: ='Sit 01'!E21 -> 0.0842145
B8: Rentabilidad depósito @WACC
B9: DEPÓSITO INVIERTO CAPEX | C9: 0 | D9: 1 | E9: 2 | F9: 3 | G9: 4 | H9: 5 | I9: 6 | J9: 7
B10: Depósito a 7 años | C10: =C3 -> -30000 | D10: =30000*$C$7 -> 2526.435 | E10: =30000*$C$7 -> 2526.435 | F10: =30000*$C$7 -> 2526.435 | G10: =30000*$C$7 -> 2526.435 | H10: =30000*$C$7 -> 2526.435 | I10: =30000*$C$7 -> 2526.435 | J10: =30000*C7 + 30000 -> 32526.435 | K10: (2) SUMA VF DEPÓSITO
B11: VF del Depósito | D11: =D10*(1+$C$7)^(7-D2) -> 4103.9248 | E11: =E10*(1+$C$7)^(7-E2) -> 3785.1595 | F11: =F10*(1+$C$7)^(7-F2) -> 3491.1537 | G11: =G10*(1+$C$7)^(7-G2) -> 3219.9844 | H11: =H10*(1+$C$7)^(7-H2) -> 2969.8776 | I11: =I10*(1+$C$7)^(7-I2) -> 2739.1975 | J11: =J10*(1+$C$7)^(7-J2) -> 32526.435 | K11: =SUM(D11:J11) -> 52835.732
B12: CF neto total Depósito | C12: =SUM(C10:C11) -> -30000 | D12: =SUM(D10:D10) -> 2526.435 | E12: =SUM(E10:E10) -> 2526.435 | F12: =SUM(F10:F10) -> 2526.435 | G12: =SUM(G10:G10) -> 2526.435 | H12: =SUM(H10:H10) -> 2526.435 | I12: =SUM(I10:I10) -> 2526.435 | J12: =SUM(J10:J10) -> 32526.435
B13: NPV Depósito | D13: =C10 + NPV('Sit 05'!$C$10, D10:J10) -> 0 | K13: (1)-(2) DIFERENCIA SUMA VF ALEMANIA Y DEPÓSITO
K14: =K5-K11 -> -5402.9829
B16: NPV Alemania: Premio de invertir Capex en Alemania en vez de un Depósito
B17: NPV Alemania | C17: =D4 -> 1729.9381
B18: NPV Depósito | C18: =D13 -> 0
B19: Premio: NPV de Alemania (la diferencia entre ambos) | C19: =C17-C20 -> 1729.9381
B21: OTRA FORMA DE VERLO
B22: (1) SUMA VF ALEMANIA | C22: =K5 -> 47432.75
B23: (2) SUMA VF DEPÓSITO | C23: =K11 -> 52835.732
B24: (1)-(2) DIFERENCIA SUMA VF ALEMANIA Y DEPÓSITO | C24: =C22-C23 -> -5402.9829
B25: Premio: VA de la Diferencia VF Alemania y Depósito
B27: ¿Quiere decir NPV Depósito = 0 que no se gana dinero con el depósito?
B29: Se gana lo equivalente al coste del dinero medido con el WACC

Sheet Sit 07
B2: Euros | C2: 0 | D2: 1 | E2: 2 | F2: 3 | G2: 4 | H2: 5 | I2: 6 | J2: 7
B3: Capex | C3: 0 | D3: -750000 | E3: -1250000 | F3: -1500000 | G3: -1000000 | H3: -500000 | I3: 0 | J3: 0
B4: Valor residual del Capex | J4: 1000000
B5: Flujo neto de Capital | C5: 0 | D5: -750000 | E5: -1250000 | F5: -1500000 | G5: -1000000 | H5: -500000 | I5: 0 | J5: 1000000
B6: NPV Costes Capital @WACC | D6: =C5 + NPV('Sit 05'!$C$10, D5:J5) -> -3421618.8
B7: TCO Capital: Coste Anual Equivalente Capital | D7: =D6 * 'Sit 05'!$C$10 / (1 - (1+'Sit 05'!$C$10)^(-7)) -> -666701.27
B9: Euros | C9: 0 | D9: 1 | E9: 2 | F9: 3 | G9: 4 | H9: 5 | I9: 6 | J9: 7
B10: Opex anual O&M Red por UUII pasada
B11: Opex anual O&M Red por UUII en servicio
B12: Flujo neto de Opex O&M de red | C12: 0 | D12: -23400 | E12: -76800 | F12: -159600 | G12: -237600 | H12: -282000 | I12: -282000 | J12: -300000
B13: NPV Costes Opex O&M @WACC | D13: =C12 + NPV('Sit 05'!$C$10, D12:J12) -> -916248.19
B14: TCO Opex O&M: Coste Anual Equivalente Opex O&M | D14: =D13 * 'Sit 05'!$C$10 / (1 - (1+'Sit 05'!$C$10)^(-7)) -> -178530.65
B16: TCO TOTAL
B17: TCO Capital: Coste Anual Equivalente Capital | D17: =D7 -> -666701.27
B18: TCO Opex O&M: Coste Anual Equivalente Opex O&M | D18: =D14 -> -178530.65
B19: TCO total | D19: =SUM(D17:D18) -> -845231.92
B22: Líneas mayoristas de fibra en servicio | C22: 5000
B24: TCO POR UI EN SERVICIO | C24: Anual | D24: Mensual
B25: TCO Capital Línea Mayorista fibra en servicio | C25: =ABS($D$17)/$C$22 -> 133.34025 | D25: =C25/12 -> 11.111688
B26: TCO Opex O&M Línea Mayorista fibra en servicio | C26: =ABS($D$18)/$C$22 -> 35.70613 | D26: =C26/12 -> 2.9755108
B27: TCO total por fibra mayorista en servicio | C27: =ABS($D$19)/$C$22 -> 169.04638 | D27: =C27/12 -> 14.087199
B28: SGA por línea | D28: =2 -> 2
B29: Costes totales por fibra mayorista en servicio (TCO total + SGA) | D29: =D27 + D28 -> 16.087199
B30: Margen de la línea mayorista de fibra | D30: 0.15
B31: Precio NEBA local (VULA) | D31: =(1+D30)*D29 -> 18.500278

Sheet Sit 08
C2: 0 | D2: 1 | E2: 2 | F2: 3 | G2: 4 | H2: 5 | I2: 6 | J2: 7
B3: Capex Servicios UI Pasada | C3: 250 | D3: 0 | E3: 0 | F3: 0 | G3: 0 | H3: 0 | I3: 0 | J3: 0
B5: Euros
B6: ARPU servicioo Universal | C6: 29.9 | D6: https://www.movistar.es/particulares/internet/adsl-fibra-optica/banda-ancha-servicio-universal/ | K6: ERROR EN EL LINK
B7: ARPU mensual Voz y BA FO | C7: 29.9 | D7: Multilique por 12 para la fila siguiente, que es anual
B8: Cobros por Servicios | C8: =12*C7 -> 358.8
B9: % EBITDA | C9: 0.18
B10: EBITDA | C10: =C8*C9 -> 64.584
B11: Pagos Opex totales | C11: =C8-C10 -> 294.216
B13: Euros | C13: 0 | D13: 1 | E13: 2 | F13: 3 | G13: 4 | H13: 5 | I13: 6 | J13: 7
B14: Cobros por Servicios | D14: =359 -> 359 | E14: =359 -> 359 | F14: =359 -> 359 | G14: =359 -> 359 | H14: =359 -> 359 | I14: =359 -> 359 | J14: =359 -> 359
B15: Ayudas anuales PEBA | C15: 0 | D15: 632.77229 | E15: 1054.6205 | F15: 1265.5446 | G15: 843.69638 | H15: 421.84819 | I15: 0 | J15: 0
B16: Cobros totales | D16: =D14+D15 -> 991.77229 | E16: =E14+E15 -> 1413.6205 | F16: =F14+F15 -> 1624.5446 | G16: =G14+G15 -> 1202.6964 | H16: =H14+H15 -> 780.84819 | I16: =I14+I15 -> 359 | J16: =J14+J15 -> 359
B17: Pagos Opex totales | D17: =-(D14-D10) -> -359 | E17: =-(E14-E10) -> -359 | F17: =-(F14-F10) -> -359 | G17: =-(G14-G10) -> -359 | H17: =-(H14-H10) -> -359 | I17: =-(I14-I10) -> -359 | J17: =-(J14-J10) -> -359
B18: Flujo de caja de Capex | C18: 0 | D18: -951.89798 | E18: -1586.4966 | F18: -1903.796 | G18: -1269.1973 | H18: -634.59865 | I18: 0 | J18: 1269.1973
B19: Pagos totales | D19: =D17+D18 -> -1310.898 | E19: =E17+E18 -> -1945.4966 | F19: =F17+F18 -> -2262.796 | G19: =G17+G18 -> -1628.1973 | H19: =H17+H18 -> -993.59865 | I19: =I17+I18 -> -359 | J19: =J17+J18 -> 910.1973
B20: Flujo neto de caja | C20: =-250 -> -250 | D20: =D16+D19 -> -319.12569 | E20: =E16+E19 -> -531.87615 | F20: =F16+F19 -> -638.25137 | G20: =G16+G19 -> -425.50092 | H20: =H16+H19 -> -212.75046 | I20: =I16+I19 -> 0 | J20: =J16+J19 -> 1269.1973
B22: WACC | C22: ='Sit 01'!E21 -> 0.0842145
B23: NPV @WACC | D23: =C20 + NPV($C$22, D20:J20) -> -1226.8532
B24: IRR | D24: =IRR(C20:J20) -> -0.13574024
B25: x IRR/WACC | D25: =C24/$C$22 -> 0

Sheet Sit 09
C2: BRASIL | D2: ESPAÑA | E2: ALEMANIA | F2: PERÚ
B3: NPV (m€) | C3: 28.609786 | D3: 32.350269 | E3: 21.29677 | F3: -0.7309782
B4: IRR | C4: 0.11517964 | D4: 0.097456912 | E4: 0.12207746 | F4: 0.10703361
B5: WACC | C5: 0.095 | D5: 0.065 | E5: 0.06 | F5: 0.11
B6: x IRR/WACC | C6: 1.2124173 | D6: 1.4993371 | E6: 2.0346244 | F6: 0.97303284
B7: Capex | C7: 760 | D7: 500 | E7: 168 | F7: 150
B8: UUII Pasadas | C8: 2000000 | D8: 1000000 | E8: 300000 | F8: 500000
B9: Factor de seguridad corporativo | C9: 1.12 | D9: 1.12 | E9: 1.12 | F9: 1.12
B10: Margen del Factor de Seguridad | C10: 0.092417261 | D10: 0.3793371 | E10: 0.91462435 | F10: -0.14696716
A11: Si/No | B11: ¿Cumple requisito obligatorio aprobación? | C11: SI | D11: SI | E11: SI | F11: NO
A12: Si/No | B12: ¿Cumple requisito mínimo corporativo aprobación?
A13: 1, 2, 3, 4 | B13: Criterio Margen del Factor de Seguridad | C13: =C4/C5 -> 1.2124173 | D13: =D4/D5 -> 1.4993371 | E13: =E4/E5 -> 2.0346244 | F13: =F4/F5 -> 0.97303284
A14: 1, 2, 3, 4 | B14: Máximo valor accionista
A15: 1, 2, 3, 4 | B15: Criterio IRR
A16: Si/No | B16: Elegibles Capital [400,800] m€
A17: Si/No | B17: Mutuamente Excluyentes ¿Cuál debe elegirse?

Sheet OLD_Sit 04
B2: Capex
B3: Deuda
B4: Plazo deuda
B5: Coste deuda
B6: Retorno anual proyectos inversión
B7: Valor final activo
B8: Coste de capital proyectos propios WAC TEF
B10: Vía Deuda | C10: 0 | D10: 0 | E10: 0 | F10: 0 | G10: 0 | H10: Total
B11: Intereses
B12: Principal
B13: Pago total
B14: Check fórmula PAGO
B16: Vía capital propio | C16: 0 | D16: 0 | E16: 0 | F16: 0 | G16: 0
B17: Capex
B18: Retorno anual
B19: Recuperación final del capital invertido
B20: CF
B21: NPV
B22: IRR
