Workbook

Sheet P1 Modelo negocio
A3: Dato | B3: Square / Block | C3: iZettle / Zettle | D3: Respuesta
A4: Sector | B4: Fintech pagos / POS | C4: Fintech pagos / POS | D4: Similares
A5: Cliente objetivo | B5: Pequeños comercios / long tail | C5: Pequeños comercios / long tail | D5: Similares
A6: Comisión por transacción | B6: 0.0275 | C6: 0.0144 | D6: Square mayor comisión
A7: Año fundación | B7: 2009 | C7: 2010 | D7: Square anterior
A8: Lanzamiento servicio | B8: 2009-2010 | C8: 2011 | D8: iZettle posterior
A9: Mercados | B9: EE.UU. + expansión | C9: Europa + México + Brasil | D9: iZettle más europeo
A10: Productos | B10: POS, Cash, Capital, Payroll | C10: POS, pagos, financiación | D10: Square más diversificado
A11: Estado 2018 | B11: Pública desde 2015 | C11: Pre-IPO / adquirida por PayPal | D11: iZettle no llegó a IPO
A12: Valoración relevante | B12: IPO: 2.900 M$ | C12: PayPal: 2.200 M$ | D12: PayPal paga premium estratégico
A13: Fortaleza | B13: Escala y cartera amplia | C13: Posición europea y sinergia PayPal | D13: Ambas fuertes en nicho pyme
A14: Debilidad | B14: EBITDA bajo / negativo histórico | C14: Sin beneficios y alta necesidad de capital | D14: Riesgo startup

Sheet P2 Cash balance
A1: P2. Cash balance 2019-2022 y capital necesario
A3: Concepto | B3: 2019 | C3: 2020 | D3: 2021 | E3: 2022 | F3: Unidad
A4: Nº POS operativos | B4: 5162500 | C4: 6453120 | D4: 8066406 | E4: 10083008 | F4: unidades
A5: Revenue anual por POS | B5: 37 | C5: 45 | D5: 54 | E5: 65 | F5: $/POS
A6: Ingresos | B6: =B4*B5/1000000 -> 191.0125 | C6: =C4*C5/1000000 -> 290.3904 | D6: =D4*D5/1000000 -> 435.58592 | E6: =E4*E5/1000000 -> 655.39552 | F6: M$
A8: Coste de ingresos | B8: 130.7 | C8: 187.2 | D8: 280.8 | E8: 329.1 | F8: M$
A9: SG&A excl. depreciación | B9: 142.4 | C9: 190.1 | D9: 223.8 | E9: 164.5 | F9: M$
A10: Capex | B10: 17.6 | C10: 26.3 | D10: 39.5 | E10: 59.2 | F10: M$
A11: Depreciación | B11: 2.3 | C11: 3.5 | D11: 5.3 | E11: 7.9 | F11: M$
A13: Cash flow usado | B13: =B6-B8-B9-B10 -> -99.6875 | C13: =C6-C8-C9-C10 -> -113.2096 | D13: =D6-D8-D9-D10 -> -108.51408 | E13: =E6-E8-E9-E10 -> 102.59552 | F13: M$
A14: Cash flow acumulado | B14: =B13 -> -99.6875 | C14: =B14+C13 -> -212.8971 | D14: =C14+D13 -> -321.41118 | E14: =D14+E13 -> -218.81566 | F14: M$
A15: Necesidad acumulada | B15: =IF(B14<0,-B14,0) -> 99.6875 | C15: =IF(C14<0,-C14,0) -> 212.8971 | D15: =IF(D14<0,-D14,0) -> 321.41118 | E15: =IF(E14<0,-E14,0) -> 218.81566 | F15: M$
A17: Capital necesario | B17: =MAX(B15:E15) -> 321.41118 | F17: M$
A18: Resultado contable incl. depreciación | B18: =B13-B11 -> -101.9875 | C18: =C13-C11 -> -116.7096 | D18: =D13-D11 -> -113.81408 | E18: =E13-E11 -> 94.69552 | F18: M$
A19: Necesidad incl. depreciación | B19: =IF(SUM($B$18:B18)<0,-SUM($B$18:B18),0) -> 101.9875 | C19: =IF(SUM($B$18:C18)<0,-SUM($B$18:C18),0) -> 218.6971 | D19: =IF(SUM($B$18:D18)<0,-SUM($B$18:D18),0) -> 332.51118 | E19: =IF(SUM($B$18:E18)<0,-SUM($B$18:E18),0) -> 237.81566 | F19: M$

Sheet P3 Valor terminal
A1: P3. Valor de salida / valor terminal
A3: Concepto | B3: Valor | C3: Unidad | D3: Fórmula / base
A4: Ingresos 2022 | B4: ='P2 Cash balance'!E6 -> 655.39552 | C4: M$ | D4: P2!E6
A5: Múltiplo usado | B5: 6.9 | C5: x | D5: Price/Sales Square IPO
A6: Valor terminal (Vt) | B6: =B4*B5 -> 4522.2291 | C6: M$ | D6: Ingresos 2022 x múltiplo
A7: Múltiplo alternativo Square 2021 | B7: 4.4 | C7: x | D7: EV/Revenue Square 2021
A8: Vt alternativo | B8: =B4*B7 -> 2883.7403 | C8: M$ | D8: Ingresos 2022 x 4,4x

Sheet P4 Vpre
A1: P4. Valor pre-financiación con IRR 40%
A3: Concepto | B3: Valor | C3: Unidad | D3: Fórmula / base
A4: Valor terminal (Vt) | B4: ='P3 Valor terminal'!B6 -> 4522.2291 | C4: M$ | D4: P3!B6
A5: IRR usada | B5: 0.4 | C5: % | D5: Dato del enunciado
A6: Tiempo hasta salida | B6: 4 | C6: años | D6: 2019-2022
A7: Valor post-money (Vpost) | B7: =B4/(1+B5)^B6 -> 1177.1733 | C7: M$ | D7: Vt / (1+IRR)^t
A8: Inversión requerida (I) | B8: ='P2 Cash balance'!B17 -> 321.41118 | C8: M$ | D8: Peak funding P2
A9: Valor pre-money (Vpre) | B9: =B7-B8 -> 855.76216 | C9: M$ | D9: Vpost - I
A10: IRR VC referencia | B10: 0.3 | C10: % | D10: Industry Ventures
A11: Loss rate early-stage | B11: 0.39 | C11: % | D11: Industry Ventures
A12: IRR mediana early-stage | B12: 0.13 | C12: % | D12: Industry Ventures

Sheet P5 Una ronda
A1: P5. Escenario de una ronda
A3: Concepto | B3: Valor | C3: Unidad | D3: Fórmula / base
A4: Inversión total (I) | B4: ='P2 Cash balance'!B17 -> 321.41118 | C4: M$ | D4: P2 capital necesario
A5: Post-money | B5: ='P4 Vpre'!B7 -> 1177.1733 | C5: M$ | D5: P4 Vpost
A6: Pre-money | B6: =B5-B4 -> 855.76216 | C6: M$ | D6: Post - I
A7: % propiedad VC (F) | B7: =B4/B5 -> 0.27303641 | C7: % | D7: I / Post
A8: % propiedad emprendedores | B8: =1-B7 -> 0.72696359 | C8: % | D8: 1-F
A9: Acciones actuales (x) | B9: 1000000 | C9: acciones | D9: Dato enunciado
A10: Nuevas acciones VC (y) | B10: =B9*B7/(1-B7) -> 375584.7 | C10: acciones | D10: x*F/(1-F)
A11: Acciones totales post | B11: =B9+B10 -> 1375584.7 | C11: acciones | D11: x+y
A12: Precio por acción | B12: =B4*1000000/B10 -> 855.76216 | C12: $/acción | D12: I/y

Sheet P6 Dos rondas
A1: P6. Escenario de dos rondas: t=0 y t=2
A3: Concepto | B3: Ronda 1 (t=0) | C3: Ronda 2 (t=2) | D3: Unidad
A4: Inversión | B4: =-SUM('P2 Cash balance'!B13:C13) -> 212.8971 | C4: =-'P2 Cash balance'!D13 -> 108.51408 | D4: M$
A5: Post-money | B5: =C6/(1+'P4 Vpre'!B5)^2 -> 1121.809 | C5: ='P3 Valor terminal'!B6/(1+'P4 Vpre'!B5)^2 -> 2307.2597 | D5: M$
A6: Pre-money | B6: =B5-B4 -> 908.91191 | C6: =C5-C4 -> 2198.7457 | D6: M$
A7: % propiedad VC | B7: =B4/B5 -> 0.18978017 | C7: =C4/C5 -> 0.047031582 | D7: %
A8: % propiedad emprendedores | B8: =1-B7 -> 0.81021983 | C8: =(1-B7)*(1-C7) -> 0.77211391 | D8: %
A9: Acciones antes de ronda | B9: 1000000 | C9: =B11 -> 1234232.9 | D9: acciones
A10: Nuevas acciones VC | B10: =B9*B7/(1-B7) -> 234232.93 | C10: =C9*C7/(1-C7) -> 60912.75 | D10: acciones
A11: Acciones totales post | B11: =B9+B10 -> 1234232.9 | C11: =C9+C10 -> 1295145.7 | D11: acciones
A12: Precio por acción | B12: =B4*1000000/B10 -> 908.91191 | C12: =C4*1000000/C10 -> 1781.4673 | D12: $/acción
A14: Propiedad final VC R1 | B14: =B7*(1-C7) -> 0.1808545 | D14: %
A15: Propiedad final VC R2 | C15: =C7 -> 0.047031582 | D15: %
A16: Propiedad final emprendedores | B16: =C8 -> 0.77211391 | D16: %

Sheet P7 PayPal
A1: P7. Comparación con adquisición de PayPal
A3: Concepto | B3: Valor | C3: Unidad | D3: Fórmula / base
A4: Precio PayPal | B4: 2200 | C4: M$ | D4: Dato caso
A5: Vpre calculado | B5: ='P4 Vpre'!B9 -> 855.76216 | C5: M$ | D5: P4 Vpre
A6: Vpost calculado | B6: ='P4 Vpre'!B7 -> 1177.1733 | C6: M$ | D6: P4 Vpost
A7: Diferencia PayPal - Vpre | B7: =B4-B5 -> 1344.2378 | C7: M$ | D7: Precio - Vpre
A8: Múltiplo PayPal / Vpre | B8: =B4/B5 -> 2.5708078 | C8: x | D8: Precio / Vpre
A9: Premium vs Vpre | B9: =B4/B5-1 -> 1.5708078 | C9: % | D9: Precio / Vpre - 1
A10: Diferencia PayPal - Vpost | B10: =B4-B6 -> 1022.8267 | C10: M$ | D10: Precio - Vpost
A11: Múltiplo PayPal / Vpost | B11: =B4/B6 -> 1.8688836 | C11: x | D11: Precio / Vpost
A12: Premium vs Vpost | B12: =B4/B6-1 -> 0.86888365 | C12: % | D12: Precio / Vpost - 1
A13: Valoración IPO prevista | B13: 1100 | C13: M$ | D13: Dato caso
A14: Diferencia Vpost - IPO prevista | B14: =B6-B13 -> 77.173336 | C14: M$ | D14: Vpost - IPO prevista
A15: Interpretación | B15: PayPal pagó 2,57x Vpre / 1,87x Vpost | D15: Premium estratégico
