Workbook

Sheet Datos principales
C2: Opción 1 | D2: Opción 2 | E2: Opción 3 | F2: Opción 4
B3: Producto principal | C3: FunSmart | D3: Excel Ultra
B4: Coste Materias Primas | C4: 38 | D4: 204
B5: Mercado | C5: Rylands | D5: Mingukia
B6: Coste Fábrica | C6: 1950000000 | D6: 1188000000
B7: Distribución internacional | C7: mayor coste | D7: menor coste
B8: Canales | C8: Minoristas | D8: Tienda online fabricante | E8: Operadoras | F8: Marketplace
B9: RRHH | C9: Operarios | D9: Ensambladores | E9: Supervisores | F9: Técnicos
B10: Costes Laborales | C10: mayor coste | D10: menor coste

Sheet Terminales
C2: ='Datos principales'!C3 -> FunSmart | D2: ='Datos principales'!D3 -> Excel Ultra | G2: =C2 -> FunSmart | H2: =D2 -> Excel Ultra
B3: Pantalla [pulgadas] | C3: 6.7 | D3: 6.7 | F3: 1 | G3: 1.662 | H3: 3.242
B4: Cámara [Mpx] | C4: 50 | D4: 50 | F4: 2 | G4: 1.68 | H4: 3.276
B5: RAM [GB] | C5: 4 | D5: 8 | F5: 3 | G5: 1.698 | H5: 3.311
B6: Batería [mAh] | C6: 5000 | D6: 4900 | F6: 4 | G6: 1.733 | H6: 3.38
B7: Garantía | C7: NO | D7: NO | F7: 5 | G7: 1.768 | H7: 3.449
B8: Funda | C8: NO | D8: NO | F8: 6 | G8: 1.786 | H8: 3.483
B9: Almacenamiento [GB] | C9: 128 | D9: 512 | F9: 7 | G9: 1.804 | H9: 3.518
B10: Calidad | F10: 8 | G10: 1.857 | H10: 3.621
B11: Resistencia acuática [min - m] | C11: NO (splashes) | D11: 30 - 1,5 | F11: 9 | G11: 1.91 | H11: 3.725
B12: Coste en Rylands | C12: =Paises!C34 -> 37 | D12: =Paises!E34 -> 34.78 | F12: 10 | G12: 1.998 | H12: 3.897
B13: Coste en Mingukia | C13: =Paises!C35 -> 121 | D13: =Paises!E35 -> 113.74
B14: Precio base materia prima* | C14: ='Datos principales'!C4 -> 38 | D14: ='Datos principales'!D4 -> 204 | F14: *Cada proveedor extra genera un gasto adicional del 5% en materias primas, dificil abastecimiento, recomendado tener mas de un proveedor

Sheet Paises
C2: ='Datos principales'!C5 -> Rylands | E2: ='Datos principales'!D5 -> Mingukia
B3: Habitantes [Mill] | C3: 335 | E3: 49* | H3: * Tasa de natalidad muy baja, alta densidad de población, tras una multiplicación de población.
B4: PIB | C4: Alto | E4: Alto | H4: *Crecio mucho en los últimos años
B5: Habitantes cualificados | C5: Alto | E5: Alto
B6: Media sueldos | C6: Alto | E6: Medio
B7: Coste contratación | C7: 1900 | E7: 1300 | H7: *imputados, integro, al inicio del ejercicio
B8: Coste formación | C8: 700 | E8: 1300 | H8: *repartidos uniforme a lo largo
B9: Coste salarial anual | C9: 35400 | E9: 27300 | H9: *repartidos de forma uniforme
B10: Formación | C10: Alto | E10: Alta
B11: Centros comerciales | C11: Alto
B12: Puntos de distribución | C12: Alto
B13: Consolidado y próspero | C13: SI | H13: *Crecio mucho en los últimos años, menos prospero y consolidado
B14: Ventas [total - comparativa] | C14: media-baja | D14: media-alta | E14: media-baja | F14: media-alta
B15: Canales de distribución
B16: ='Datos principales'!C8 -> Minoristas | C16: 32% - 76% | D16: 10% - 24% | E16: 17% - 46% | F16: 19% - 54%
B17: Costes fijos anuales | C17: 5746312 | E17: 4467212
B18: Comisión sobre ventas | C18: 0.06 | E18: 0.05
B19: ='Datos principales'!D8 -> Tienda online fabricante | C19: 16% - 29% | D19: 38% - 71% | E19: 21% - 50% | F19: 21% - 50%
B20: Costes fijos anuales | C20: 1054922 | E20: 854922
B21: Comisión sobre ventas | C21: 0 | E21: 0
B22: ='Datos principales'!E8 -> Operadoras | C22: 9% - 30% | D22: 21% - 70% | E22: 20% - 41% | F22: 29% - 59%
B23: Costes fijos anuales | C23: 9857653 | E23: 11556412
B24: Comisión sobre ventas | C24: 0.09 | E24: 0.1
B25: ='Datos principales'!F8 -> Marketplace | C25: 43% - 58% | D25: 31% - 42% | E25: 42% - 57% | F25: 31% - 43%
B26: Costes fijos anuales | C26: 15742370 | E26: 18427073
B27: Comisión sobre ventas | C27: 0.17 | E27: 12
B28: Gente con móvil [%] | C28: 87.8
B29: Trafico web por movil [%] | C29: 47
B30: Comprar móvil nuevo [%] | C30: 2.55 | E30: 12,5% (60% alto - 40% baja)
B31: Plantear móvil nuevo [%] | C31: 6.9 | H31: *País muy sensible a las modas
B32: ='Datos principales'!B6 -> Coste Fábrica | C32: ='Datos principales'!C6 -> 1950000000 | E32: ='Datos principales'!D6 -> 1188000000
B33: Costes Fábrica anuales extra | C33: =C32 * 0.2 -> 390000000 | E33: =E32 * 0.2 -> 237600000
B34: Coste fabricación FunSmart | C34: 37 | E34: 34.78
B35: Coste fabricación Excel | C35: 121 | E35: 113.74

Sheet Operaciones
E1: Costes de distribución
C2: Estructura de la fábrica [nº] | G2: DEST | J2: RRHH
B3: Máquinas | C3: 100 | G3: Rylands | H3: Mingukia | J3: Operarios especializados
B4: Operarios de fabricación | C4: 200 | E4: ORIG. | F4: Rylands | G4: 5 | H4: 23 | J4: Operarios no especializados | M4: * Difieren costes de contratación y formación en cada pais
B5: Operarios de ensamblado | C5: 400 | F5: Mingukia | G5: 32 | H5: 4 | J5: Supervisores de calidad | M5: * De productividad tambien
B6: Supervisores de calidad | C6: 100 | J6: Técnicos de mantenimiento
B7: Técnicos de mantenimiento | C7: 100
J9: Intervalos distribución datos
C10: Organización | E10: Funcionalidad | H10: Coste ud | J10: I1 | K10: +75%
B11: Turnos (8h) | C11: 8-16 / 16-00 | E11: Extensión de garantía obligatoria | H11: 8.29 | J11: I2 | K11: +50%
B12: Jornada laboral [h/sem] | C12: 40 | E12: Funda protectora incluida | H12: 4.37 | J12: I3 | K12: +25%
B13: Vacaciones [sem] | C13: 4 | E13: +1 GB de RAM | H13: 7
B14: Operarios Fabricación / maq | C14: 1 | E14: +2 GB de RAM | H14: 13 | J14: Cualificación | M14: * Afecta en costes y en clima y formacion
B15: Operarios Ensamblado / maq | C15: 2 | E15: +3 GB de RAM | H15: 24 | J15: Experto | M15: * Afecta en la productividad
B16: Supervisor / maq | C16: 0.5 | E16: +4 GB de RAM | H16: 30 | J16: Avanzado
B17: Técnico Mantenimiento / maq | C17: 0.5 | E17: +8 GB de RAM | H17: 55 | J17: Básico

Sheet Trade Marketing
